{"cameraMode":{"drawMode":0,"name":"Shaded","section":"Shading Mode"},"sceneLighting":false,"audioPlay":false,"sceneViewState":{"m_AlwaysRefresh":false,"showFog":true,"showSkybox":false,"showFlares":true,"showImageEffects":true,"showParticleSystems":true,"showVisualEffectGraphs":true,"m_FxEnabled":true},"in2DMode":false,"pivot":{"x":-35.13999938964844,"y":2.5399999618530275,"z":-50.099998474121097},"rotation":{"x":-0.0009589246474206448,"y":0.9145734310150147,"z":-0.40447744727134707,"w":-0.00219016894698143},"size":2.9159047603607179,"orthographic":false}